arbor-0.11.0.dist-info/RECORD
arbor-0.11.0.dist-info/WHEEL
arbor-0.11.0.dist-info/entry_points.txt
arbor-0.11.0.dist-info/METADATA
arbor-0.11.0.dist-info/licenses/LICENSE
arbor/LICENSE
arbor/__init__.pyi
arbor/__init__.py
arbor/_arbor.cpython-311-darwin.so
arbor/README.md
arbor/VERSION
arbor/_arbor/__init__.pyi
arbor/_arbor/units.pyi
arbor/_arbor/env.pyi
arbor/bin/modcc
arbor/bin/lmorpho
arbor/bin/arbor-build-catalogue
arbor/include/benchmark/export.h
arbor/include/benchmark/benchmark.h
arbor/include/arborenv/concurrency.hpp
arbor/include/arborenv/export.hpp
arbor/include/arborenv/default_env.hpp
arbor/include/arborenv/gpu_env.hpp
arbor/include/arborenv/with_mpi.hpp
arbor/include/arborenv/arbenvexcept.hpp
arbor/include/fmt/ostream.h
arbor/include/fmt/format-inl.h
arbor/include/fmt/ranges.h
arbor/include/fmt/xchar.h
arbor/include/fmt/core.h
arbor/include/fmt/chrono.h
arbor/include/fmt/os.h
arbor/include/fmt/color.h
arbor/include/fmt/args.h
arbor/include/fmt/printf.h
arbor/include/fmt/compile.h
arbor/include/fmt/format.h
arbor/include/fmt/std.h
arbor/include/arborio/neurolucida.hpp
arbor/include/arborio/json_serdes.hpp
arbor/include/arborio/export.hpp
arbor/include/arborio/networkio.hpp
arbor/include/arborio/cv_policy_parse.hpp
arbor/include/arborio/debug.hpp
arbor/include/arborio/neuroml.hpp
arbor/include/arborio/swcio.hpp
arbor/include/arborio/loaded_morphology.hpp
arbor/include/arborio/cableio.hpp
arbor/include/arborio/label_parse.hpp
arbor/include/arbor/common_types.hpp
arbor/include/arbor/arb_types.hpp
arbor/include/arbor/spike_source_cell.hpp
arbor/include/arbor/simulation.hpp
arbor/include/arbor/sampling.hpp
arbor/include/arbor/load_balance.hpp
arbor/include/arbor/domain_decomposition.hpp
arbor/include/arbor/s_expr.hpp
arbor/include/arbor/cable_cell_param.hpp
arbor/include/arbor/export.hpp
arbor/include/arbor/mechinfo.hpp
arbor/include/arbor/arb_types.h
arbor/include/arbor/spike_event.hpp
arbor/include/arbor/arb_types.inc
arbor/include/arbor/iexpr.hpp
arbor/include/arbor/cv_policy.hpp
arbor/include/arbor/lif_cell.hpp
arbor/include/arbor/spike.hpp
