Metadata-Version: 2.4
Name: arbor
Version: 0.11.0
Summary: High performance simulation of networks of multicompartment neurons.
Keywords: simulator,neuroscience,morphological detail,HPC,GPU,C++
Author-Email: Arbor Dev Team <contact@arbor-sim.org>
Maintainer-Email: Arbor Dev Team <contact@arbor-sim.org>
License-Expression: BSD-3-Clause
License-File: LICENSE
Classifier: Development Status :: 5 - Production/Stable
Classifier: Intended Audience :: Science/Research
Classifier: Programming Language :: Python
Classifier: Programming Language :: Python :: 3.10
Classifier: Programming Language :: Python :: 3.11
Classifier: Programming Language :: Python :: 3.12
Classifier: Programming Language :: Python :: 3.13
Classifier: Programming Language :: C++
Project-URL: homepage, https://arbor-sim.org
Project-URL: documentation, https://docs.arbor-sim.org
Project-URL: repository, https://github.com/arbor-sim/arbor
Project-URL: changelog, https://github.com/arbor-sim/arbor/releases
Requires-Python: >=3.10
Requires-Dist: numpy
